mkdocs_latest_version_tag_plugin/__init__.py
mkdocs_latest_version_tag_plugin/plugin.py
mkdocs_latest_version_tag_plugin-0.1.2.dist-info/entry_points.txt
mkdocs_latest_version_tag_plugin-0.1.2.dist-info/WHEEL
mkdocs_latest_version_tag_plugin-0.1.2.dist-info/METADATA
mkdocs_latest_version_tag_plugin-0.1.2.dist-info/license_files/LICENSE
mkdocs_latest_version_tag_plugin-0.1.2.dist-info/RECORD
