Metadata-Version: 2.1
Name: mkdocs_latest_version_tag_plugin
Version: 0.1.2
Summary: UNKNOWN
License: MIT
Author-email: Michael Kalashnikov <kalashnikovsystem@gmail.com>
Requires-Python: >=3.10
Requires-Dist: httpx>=0.22.0
Requires-Dist: mkdocs>=1.2.3
Project-URL: Homepage, https://github.com/m-v-kalashnikov/mkdocs_latest_version_tag_plugin
